Metadata-Version: 2.1
Name: fjgu-probability
Version: 0.2
Summary: Gaussian and Binomial Distributions
Home-page: UNKNOWN
Author: franco Gutierrez
License: UNKNOWN
Platform: UNKNOWN
License-File: license.txt
